kinto_remote_settings/__init__.py
kinto_remote_settings/changes/__init__.py
kinto_remote_settings/changes/utils.py
kinto_remote_settings/changes/views.py
kinto_remote_settings/changes/tests/__init__.py
kinto_remote_settings/changes/tests/test_changes.py
kinto_remote_settings/changes/tests/test_changeset.py
kinto_remote_settings/changes/tests/test_utils.py
kinto_remote_settings/signer/__init__.py
kinto_remote_settings/signer/events.py
kinto_remote_settings/signer/generate_keypair.py
kinto_remote_settings/signer/listeners.py
kinto_remote_settings/signer/serializer.py
kinto_remote_settings/signer/updater.py
kinto_remote_settings/signer/utils.py
kinto_remote_settings/signer/backends/__init__.py
kinto_remote_settings/signer/backends/autograph.py
kinto_remote_settings/signer/backends/base.py
kinto_remote_settings/signer/backends/exceptions.py
kinto_remote_settings/signer/backends/local_ecdsa.py
kinto_remote_settings/signer/tests/__init__.py
kinto_remote_settings/signer/tests/functional.py
kinto_remote_settings/signer/tests/support.py
kinto_remote_settings/signer/tests/test_events.py
kinto_remote_settings/signer/tests/test_generate_keypair.py
kinto_remote_settings/signer/tests/test_plugin_setup.py
kinto_remote_settings/signer/tests/test_serializer.py
kinto_remote_settings/signer/tests/test_signer.py
kinto_remote_settings/signer/tests/test_signer_attachments.py
kinto_remote_settings/signer/tests/test_signoff_flow.py
kinto_remote_settings/signer/tests/test_updater.py
kinto_remote_settings/signer/tests/test_utils.py
kinto_dist-27.0.3.dist-info/LICENSE
kinto_dist-27.0.3.dist-info/METADATA
kinto_dist-27.0.3.dist-info/WHEEL
kinto_dist-27.0.3.dist-info/top_level.txt
kinto_dist-27.0.3.dist-info/RECORD
