Metadata-Version: 2.1
Name: kinto-dist
Version: 27.0.3
Summary: Kinto Distribution
Home-page: https://github.com/mozilla-services/kinto-dist
Author: Mozilla Services
Author-email: services-dev@mozilla.com
License: Apache License (2.0)
Keywords: web services
Platform: UNKNOWN
Classifier: Programming Language :: Python
Classifier: Programming Language :: Python :: 3
Classifier: Programming Language :: Python :: 3.5
Classifier: Programming Language :: Python :: 3.6
Classifier: Programming Language :: Python :: Implementation :: CPython
Classifier: Programming Language :: Python :: Implementation :: PyPy
Classifier: Topic :: Internet :: WWW/HTTP
Classifier: Topic :: Internet :: WWW/HTTP :: WSGI :: Application
Classifier: License :: OSI Approved :: Apache Software License
Requires-Dist: attrs (==21.2.0)
Requires-Dist: bcrypt (==3.2.0)
Requires-Dist: boto (==2.49.0)
Requires-Dist: canonicaljson-rs (==0.3.0)
Requires-Dist: certifi (==2021.10.8)
Requires-Dist: cffi (==1.15.0)
Requires-Dist: charset-normalizer (==2.0.7)
Requires-Dist: colander (==1.8.3)
Requires-Dist: colorama (==0.4.4)
Requires-Dist: cornice (==6.0.0)
Requires-Dist: cornice-swagger (==1.0.1)
Requires-Dist: dockerflow (==2021.7.0)
Requires-Dist: ec2-metadata (==2.6.0)
Requires-Dist: ecdsa (==0.17.0)
Requires-Dist: greenlet (==1.1.2)
Requires-Dist: hupper (==1.10.3)
Requires-Dist: idna (==3.3)
Requires-Dist: iso8601 (==1.0.0)
Requires-Dist: jsonpatch (==1.32)
Requires-Dist: jsonpointer (==2.2)
Requires-Dist: jsonschema (==4.2.1)
Requires-Dist: kinto[monitoring,postgresql] (==14.6.0)
Requires-Dist: kinto-attachment (==6.2.0)
Requires-Dist: kinto-emailer (==2.1.0)
Requires-Dist: logging-color-formatter (==1.0.2)
Requires-Dist: mohawk (==1.1.0)
Requires-Dist: newrelic (==7.2.3.170)
Requires-Dist: pastedeploy (==2.1.1)
Requires-Dist: plaster (==1.0)
Requires-Dist: plaster-pastedeploy (==0.7)
Requires-Dist: psycopg2 (==2.9.1)
Requires-Dist: pycparser (==2.21)
Requires-Dist: pyramid (==2.0)
Requires-Dist: pyramid-mailer (==0.15.1)
Requires-Dist: pyramid-multiauth (==1.0.1)
Requires-Dist: pyramid-storage (==1.0.0)
Requires-Dist: pyramid-tm (==2.4)
Requires-Dist: pyrsistent (==0.18.0)
Requires-Dist: python-dateutil (==2.8.2)
Requires-Dist: python-memcached (==1.59)
Requires-Dist: python-rapidjson (==1.5)
Requires-Dist: raven (==6.10.0)
Requires-Dist: repoze.sendmail (==4.4.1)
Requires-Dist: requests (==2.26.0)
Requires-Dist: requests-hawk (==1.1.1)
Requires-Dist: six (==1.16.0)
Requires-Dist: sqlalchemy (==1.4.26)
Requires-Dist: statsd (==3.3.0)
Requires-Dist: transaction (==3.0.1)
Requires-Dist: translationstring (==1.4)
Requires-Dist: urllib3 (==1.26.7)
Requires-Dist: uwsgi (==2.0.20)
Requires-Dist: venusian (==3.0.0)
Requires-Dist: waitress (==2.0.0)
Requires-Dist: webob (==1.8.7)
Requires-Dist: werkzeug (==2.0.2)
Requires-Dist: zope.deprecation (==4.4.0)
Requires-Dist: zope.interface (==5.4.0)
Requires-Dist: zope.sqlalchemy (==1.6)
